Metadata-Version: 1.0
Name: yalecourses
Version: 0.1.5
Summary: Library for fetching data from the Yale Courses API.
Home-page: https://github.com/ErikBoesen/yalecourses
Author: Erik Boesen
Author-email: me@erikboesen.com
License: GPL
Platform: UNKNOWN
